{
  "schema_version": "1.0",
  "patient_id": "PAT-MOD-006",
  "demographics": {
    "name": "Mona Fawzy",
    "date_of_birth": "1992-07-07",
    "sex": "female"
  },
  "conditions": [
    "HTN"
  ],
  "allergy_registry": [],
  "visits": [
    {
      "visit_id": "VST-MOD-006-001",
      "visit_date": "2023-06-10",
      "visit_type": "initial",
      "attending_physician": "Dr. Salma Nabil",
      "diagnoses": [
        "HTN"
      ],
      "vitals": {
        "bp_systolic": 154,
        "bp_diastolic": 96,
        "heart_rate": 82,
        "weight_kg": 66.2,
        "bmi": 23.2
      },
      "labs": [],
      "medications": [
        {
          "medication_name": "Lisinopril",
          "medication_class": "ACE Inhibitor",
          "dose": "10 mg",
          "frequency": "once_daily",
          "route": "oral",
          "start_date": "2023-06-10",
          "stop_date": null
        }
      ],
      "soap_note": {
        "subjective": "The chart documents a 30-year-old female patient seen for a initial visit. The condition list records HTN. The patient-level condition field documents hypertension. This is documented as the first encounter type in the visit record.",
        "objective": "Objective data from the encounter records blood pressure 154/96 mmHg, heart rate 82 bpm, weight 66.2 kg, and BMI 23.2. Laboratory results: no lab results recorded. No laboratory entries are documented for this visit. Linked document references: DOC-MOD-006-001.",
        "assessment": "Diagnoses documented for this visit are summarized as HTN. The visit diagnosis field documents hypertension for this encounter. Retrieval focus includes patient-level conditions: hypertension; visit diagnoses: hypertension; medication entries: lisinopril; visit type: initial; timeline link: first documented visit.",
        "plan": "The plan section records the active medication entries as documented: Lisinopril 10 mg once_daily via oral. The medication list includes documented entries related to hypertension medication documentation. This is the first recorded visit in the available record."
      },
      "linked_documents": [
        "DOC-MOD-006-001"
      ],
      "prior_visit_id": null
    },
    {
      "visit_id": "VST-MOD-006-002",
      "visit_date": "2023-08-09",
      "visit_type": "follow_up",
      "attending_physician": "Dr. Ahmed Farid",
      "diagnoses": [
        "HTN"
      ],
      "vitals": {
        "bp_systolic": 152,
        "bp_diastolic": 95,
        "heart_rate": 81,
        "weight_kg": 65.8,
        "bmi": 23.1
      },
      "labs": [],
      "medications": [
        {
          "medication_name": "Lisinopril",
          "medication_class": "ACE Inhibitor",
          "dose": "10 mg",
          "frequency": "once_daily",
          "route": "oral",
          "start_date": "2023-06-10",
          "stop_date": null
        }
      ],
      "soap_note": {
        "subjective": "During this follow_up encounter, the record identifies a 31-year-old female patient. The condition list includes HTN. The patient-level condition field documents hypertension. Retrieval focus includes patient-level conditions: hypertension; visit diagnoses: hypertension; medication entries: lisinopril; visit type: follow_up; timeline link: prior visit documented.",
        "objective": "Objective findings record blood pressure 152/95 mmHg, heart rate 81 bpm, weight 65.8 kg, and BMI 23.1. Laboratory results for this visit: no lab results recorded. No laboratory entries are documented for this visit. Linked document references: DOC-MOD-006-002.",
        "assessment": "The recorded assessment for this encounter is based on the visit diagnosis list: HTN. The visit diagnosis field documents hypertension for this encounter. No laboratory entries are documented for this visit.",
        "plan": "The visit plan lists the medication entries documented in the record: Lisinopril 10 mg once_daily via oral. The medication list includes documented entries related to hypertension medication documentation. Prior visit reference is VST-MOD-006-001. This encounter is linked to a prior documented visit through prior_visit_id VST-MOD-006-001."
      },
      "linked_documents": [
        "DOC-MOD-006-002"
      ],
      "prior_visit_id": "VST-MOD-006-001"
    },
    {
      "visit_id": "VST-MOD-006-003",
      "visit_date": "2023-10-08",
      "visit_type": "follow_up",
      "attending_physician": "Dr. Laila Mostafa",
      "diagnoses": [
        "HTN"
      ],
      "vitals": {
        "bp_systolic": 150,
        "bp_diastolic": 94,
        "heart_rate": 80,
        "weight_kg": 65.4,
        "bmi": 23.0
      },
      "labs": [],
      "medications": [
        {
          "medication_name": "Lisinopril",
          "medication_class": "ACE Inhibitor",
          "dose": "10 mg",
          "frequency": "once_daily",
          "route": "oral",
          "start_date": "2023-06-10",
          "stop_date": null
        }
      ],
      "soap_note": {
        "subjective": "The chart documents a 31-year-old female patient seen for a follow_up visit. The condition list records HTN. The patient-level condition field documents hypertension. This is documented as a follow-up encounter in the visit record.",
        "objective": "Structured objective data lists blood pressure 150/94 mmHg, heart rate 80 bpm, weight 65.4 kg, and BMI 23.0. Lab results documented for the visit: no lab results recorded. No laboratory entries are documented for this visit. Linked document references: DOC-MOD-006-003.",
        "assessment": "Assessment summarizes the diagnoses documented for this visit: HTN. The visit diagnosis field documents hypertension for this encounter. The patient-level condition field documents hypertension.",
        "plan": "The plan section records the active medication entries as documented: Lisinopril 10 mg once_daily via oral. The medication list includes documented entries related to hypertension medication documentation. Prior visit reference is VST-MOD-006-002."
      },
      "linked_documents": [
        "DOC-MOD-006-003"
      ],
      "prior_visit_id": "VST-MOD-006-002"
    },
    {
      "visit_id": "VST-MOD-006-004",
      "visit_date": "2023-12-07",
      "visit_type": "follow_up",
      "attending_physician": "Dr. Hany Fawzy",
      "diagnoses": [
        "HTN"
      ],
      "vitals": {
        "bp_systolic": 148,
        "bp_diastolic": 93,
        "heart_rate": 79,
        "weight_kg": 65.0,
        "bmi": 22.8
      },
      "labs": [],
      "medications": [
        {
          "medication_name": "Lisinopril",
          "medication_class": "ACE Inhibitor",
          "dose": "10 mg",
          "frequency": "once_daily",
          "route": "oral",
          "start_date": "2023-06-10",
          "stop_date": null
        }
      ],
      "soap_note": {
        "subjective": "This follow_up note describes a 31-year-old female patient. Conditions recorded in the chart are HTN. This is documented as a follow-up encounter in the visit record. The patient-level condition field documents hypertension.",
        "objective": "The visit measurements include blood pressure 148/93 mmHg, heart rate 79 bpm, weight 65.0 kg, and BMI 22.8. Laboratory entries are recorded as: no lab results recorded. No laboratory entries are documented for this visit. Linked document references: DOC-MOD-006-004.",
        "assessment": "Assessment summarizes the diagnoses documented for this visit: HTN. The visit diagnosis field documents hypertension for this encounter. The patient-level condition field documents hypertension.",
        "plan": "The visit plan lists the medication entries documented in the record: Lisinopril 10 mg once_daily via oral. The medication list includes documented entries related to hypertension medication documentation. Prior visit reference is VST-MOD-006-003. This encounter is linked to a prior documented visit through prior_visit_id VST-MOD-006-003."
      },
      "linked_documents": [
        "DOC-MOD-006-004"
      ],
      "prior_visit_id": "VST-MOD-006-003"
    },
    {
      "visit_id": "VST-MOD-006-005",
      "visit_date": "2024-03-06",
      "visit_type": "follow_up",
      "attending_physician": "Dr. Mona Kareem",
      "diagnoses": [
        "HTN"
      ],
      "vitals": {
        "bp_systolic": 146,
        "bp_diastolic": 92,
        "heart_rate": 78,
        "weight_kg": 64.6,
        "bmi": 22.7
      },
      "labs": [],
      "medications": [
        {
          "medication_name": "Lisinopril",
          "medication_class": "ACE Inhibitor",
          "dose": "10 mg",
          "frequency": "once_daily",
          "route": "oral",
          "start_date": "2023-06-10",
          "stop_date": null
        },
        {
          "medication_name": "Amlodipine",
          "medication_class": "Calcium Channel Blocker",
          "dose": "5 mg",
          "frequency": "once_daily",
          "route": "oral",
          "start_date": "2024-03-06",
          "stop_date": null
        }
      ],
      "soap_note": {
        "subjective": "This follow_up note describes a 31-year-old female patient. Conditions recorded in the chart are HTN. This is documented as a follow-up encounter in the visit record. The patient-level condition field documents hypertension.",
        "objective": "The visit measurements include blood pressure 146/92 mmHg, heart rate 78 bpm, weight 64.6 kg, and BMI 22.7. Laboratory entries are recorded as: no lab results recorded. No laboratory entries are documented for this visit. Linked document references: DOC-MOD-006-005.",
        "assessment": "The visit diagnosis list records HTN. The visit diagnosis field documents hypertension for this encounter. The patient-level condition field documents hypertension.",
        "plan": "The documented plan includes the following medication entries: Lisinopril 10 mg once_daily via oral; Amlodipine 5 mg once_daily via oral. The medication list includes documented entries related to hypertension medication documentation. Prior visit reference is VST-MOD-006-004. Retrieval focus includes patient-level conditions: hypertension; visit diagnoses: hypertension; medication entries: amlodipine and lisinopril; visit type: follow_up; timeline link: prior visit documented."
      },
      "linked_documents": [
        "DOC-MOD-006-005"
      ],
      "prior_visit_id": "VST-MOD-006-004"
    },
    {
      "visit_id": "VST-MOD-006-006",
      "visit_date": "2024-06-04",
      "visit_type": "follow_up",
      "attending_physician": "Dr. Yasser Amin",
      "diagnoses": [
        "HTN"
      ],
      "vitals": {
        "bp_systolic": 144,
        "bp_diastolic": 91,
        "heart_rate": 78,
        "weight_kg": 64.2,
        "bmi": 22.6
      },
      "labs": [],
      "medications": [
        {
          "medication_name": "Lisinopril",
          "medication_class": "ACE Inhibitor",
          "dose": "10 mg",
          "frequency": "once_daily",
          "route": "oral",
          "start_date": "2023-06-10",
          "stop_date": null
        },
        {
          "medication_name": "Amlodipine",
          "medication_class": "Calcium Channel Blocker",
          "dose": "5 mg",
          "frequency": "once_daily",
          "route": "oral",
          "start_date": "2024-03-06",
          "stop_date": null
        }
      ],
      "soap_note": {
        "subjective": "The chart documents a 31-year-old female patient seen for a follow_up visit. The condition list records HTN. The patient-level condition field documents hypertension. This is documented as a follow-up encounter in the visit record.",
        "objective": "Objective findings record blood pressure 144/91 mmHg, heart rate 78 bpm, weight 64.2 kg, and BMI 22.6. Laboratory results for this visit: no lab results recorded. No laboratory entries are documented for this visit. Linked document references: DOC-MOD-006-006.",
        "assessment": "Assessment summarizes the diagnoses documented for this visit: HTN. The visit diagnosis field documents hypertension for this encounter. The patient-level condition field documents hypertension.",
        "plan": "The visit plan lists the medication entries documented in the record: Lisinopril 10 mg once_daily via oral; Amlodipine 5 mg once_daily via oral. The medication list includes documented entries related to hypertension medication documentation. Prior visit reference is VST-MOD-006-005. This encounter is linked to a prior documented visit through prior_visit_id VST-MOD-006-005."
      },
      "linked_documents": [
        "DOC-MOD-006-006"
      ],
      "prior_visit_id": "VST-MOD-006-005"
    },
    {
      "visit_id": "VST-MOD-006-007",
      "visit_date": "2024-09-02",
      "visit_type": "follow_up",
      "attending_physician": "Dr. Salma Nabil",
      "diagnoses": [
        "HTN"
      ],
      "vitals": {
        "bp_systolic": 142,
        "bp_diastolic": 90,
        "heart_rate": 78,
        "weight_kg": 63.8,
        "bmi": 22.5
      },
      "labs": [],
      "medications": [
        {
          "medication_name": "Lisinopril",
          "medication_class": "ACE Inhibitor",
          "dose": "10 mg",
          "frequency": "once_daily",
          "route": "oral",
          "start_date": "2023-06-10",
          "stop_date": null
        },
        {
          "medication_name": "Amlodipine",
          "medication_class": "Calcium Channel Blocker",
          "dose": "5 mg",
          "frequency": "once_daily",
          "route": "oral",
          "start_date": "2024-03-06",
          "stop_date": null
        }
      ],
      "soap_note": {
        "subjective": "A 32-year-old female patient is recorded for a follow_up visit. The documented condition list includes HTN. The patient-level condition field documents hypertension. This encounter is linked to a prior documented visit through prior_visit_id VST-MOD-006-006.",
        "objective": "Objective data from the encounter records blood pressure 142/90 mmHg, heart rate 78 bpm, weight 63.8 kg, and BMI 22.5. Laboratory results: no lab results recorded. No laboratory entries are documented for this visit. Linked document references: DOC-MOD-006-007.",
        "assessment": "Assessment summarizes the diagnoses documented for this visit: HTN. The visit diagnosis field documents hypertension for this encounter. The patient-level condition field documents hypertension.",
        "plan": "The visit plan lists the medication entries documented in the record: Lisinopril 10 mg once_daily via oral; Amlodipine 5 mg once_daily via oral. The medication list includes documented entries related to hypertension medication documentation. Prior visit reference is VST-MOD-006-006. This encounter is linked to a prior documented visit through prior_visit_id VST-MOD-006-006."
      },
      "linked_documents": [
        "DOC-MOD-006-007"
      ],
      "prior_visit_id": "VST-MOD-006-006"
    }
  ],
  "metadata": {
    "tier": "moderate"
  }
}